MagicChef/__init__.py
MagicChef/browser.py
MagicChef/scraper.py
MagicChef-1.0.0.dist-info/LICENSE
MagicChef-1.0.0.dist-info/METADATA
MagicChef-1.0.0.dist-info/WHEEL
MagicChef-1.0.0.dist-info/top_level.txt
MagicChef-1.0.0.dist-info/RECORD
