Metadata-Version: 2.1
Name: MagicChef
Version: 1.0.0
Summary: MagicChef is a Python library designed to automatically detect and decode encrypted text using the MagicChef web interface. You simply provide an encoded string, and the library processes it to identify the encryption type and return the decoded result in structured JSON format.
Author: deep
Author-email: asyncpy@gmail.com
License: MIT
Classifier: Programming Language :: Python :: 3
Classifier: License :: OSI Approved :: MIT License
Classifier: Operating System :: OS Independent
Requires-Python: >=3.6
License-File: LICENSE
